apigwsgi
