Metadata-Version: 1.1
Name: apigwsgi
Version: 0.1.5
Summary: WSGI compatibility for AWS API Gateway proxy resources
Home-page: https://github.com/nathforge/apigwsgi
Author: Nathan Reynolds
Author-email: email@nreynolds.co.uk
License: UNKNOWN
Platform: UNKNOWN
Classifier: Development Status :: 4 - Beta
Classifier: Intended Audience :: Developers
Classifier: Topic :: Software Development
Classifier: License :: OSI Approved :: MIT License
Classifier: Programming Language :: Python :: 2.7
